sparse/__init__.py
sparse/base.py
sparse/cat.py
sparse/indexing.py
sparse/mapping.py
sparse/mask.py
sparse/ops.py
sparse/scatter.py
sparse/shape.py
sparse/sparse.py
sparse/type.py
sparse/typing.py
torch_sparse_tensor-0.2.0.dist-info/METADATA
torch_sparse_tensor-0.2.0.dist-info/WHEEL
torch_sparse_tensor-0.2.0.dist-info/RECORD
